compas_masonry/__init__.py
compas_masonry/__main__.py
compas_masonry/session.py
compas_masonry/settings.py
compas_masonry/splash.py
compas_masonry/forms/__init__.py
compas_masonry/forms/settings.py
compas_masonry/scene/__init__.py
compas_masonry/scene/blockobject.py
compas_masonry/scene/contactobject.py
compas_masonry/scene/formobject.py
compas_masonry/scene/igraphobject.py
compas_masonry/viewers/__init__.py
compas_masonry/viewers/masonryviewer.py
compas_masonry-0.3.0.dist-info/licenses/LICENSE
compas_masonry-0.3.0.dist-info/METADATA
compas_masonry-0.3.0.dist-info/WHEEL
compas_masonry-0.3.0.dist-info/top_level.txt
compas_masonry-0.3.0.dist-info/RECORD
