Metadata-Version: 2.4
Name: compas_masonry
Version: 0.3.0
Summary: COMPAS Masonry is a masonry assessment toolbox for Rhino based on the COMPAS framework.
Author-email: tom van mele <tom.v.mele@gmail.com>
License: MIT License
Project-URL: Homepage, https://blockresearchgroup.github.io/compas_masonry
Project-URL: Documentation, https://blockresearchgroup.github.io/compas_masonry
Project-URL: Repository, https://github.com/blockresearchgroup/compas_masonry
Project-URL: Changelog, https://github.com/blockresearchgroup/compas_masonry/blob/main/CHANGELOG.md
Project-URL: Issues, https://github.com/blockresearchgroup/compas_masonry/issues
Project-URL: Forum, https://forum.compas-framework.org/
Classifier: Development Status :: 4 - Beta
Classifier: Topic :: Scientific/Engineering
Classifier: Operating System :: Unix
Classifier: Operating System :: POSIX
Classifier: Operating System :: Microsoft :: Windows
Classifier: Programming Language :: Python
Classifier: Programming Language :: Python :: 3
Classifier: Programming Language :: Python :: 3.9
Classifier: Programming Language :: Python :: 3.10
Classifier: Programming Language :: Python :: 3.11
Requires-Python: >=3.9
License-File: LICENSE
Requires-Dist: compas>=2.14.1
Requires-Dist: compas_cgal>=0.9.1
Requires-Dist: compas_dem>=0.4.2
Requires-Dist: compas_libigl>=0.7.6
Requires-Dist: compas_rui>=0.6
Requires-Dist: compas_session>=0.7
Requires-Dist: compas_tna>=0.7
Requires-Dist: compas_tno>=0.3
Provides-Extra: dev
Requires-Dist: bump-my-version; extra == "dev"
Requires-Dist: compas_invocations2; extra == "dev"
Requires-Dist: invoke>=0.14; extra == "dev"
Requires-Dist: ruff; extra == "dev"
Requires-Dist: sphinx_compas2_theme; extra == "dev"
Requires-Dist: twine; extra == "dev"
Requires-Dist: wheel; extra == "dev"
Provides-Extra: viz
Requires-Dist: compas_notebook; extra == "viz"
Requires-Dist: compas_viewer; extra == "viz"
Dynamic: license-file
